{
  "version": "6",
  "dialect": "sqlite",
  "id": "34547107-95a7-400c-b1e9-1447e2bb1e26",
  "prevId": "d4f7842c-1b9b-4e1a-ab50-1a940397a69a",
  "tables": {
    "api_keys": {
      "name": "api_keys",
      "columns": {
        "salt": {
          "name": "salt",
          "type": "text",
          "primaryKey": true,
          "notNull": true,
          "autoincrement": false
        },
        "key": {
          "name": "key",
          "type": "text",
          "primaryKey": false,
          "notNull": true,
          "autoincrement": false
        },
        "created_at": {
          "name": "created_at",
          "type": "text",
          "primaryKey": false,
          "notNull": true,
          "autoincrement": false,
          "default": "(strftime('%Y-%m-%dT%H:%M:%SZ', 'now'))"
        }
      },
      "indexes": {},
      "foreignKeys": {},
      "compositePrimaryKeys": {},
      "uniqueConstraints": {}
    },
    "packages": {
      "name": "packages",
      "columns": {
        "name": {
          "name": "name",
          "type": "text",
          "primaryKey": false,
          "notNull": true,
          "autoincrement": false
        },
        "pname": {
          "name": "pname",
          "type": "text",
          "primaryKey": false,
          "notNull": true,
          "autoincrement": false
        },
        "version": {
          "name": "version",
          "type": "text",
          "primaryKey": false,
          "notNull": true,
          "autoincrement": false
        },
        "nix": {
          "name": "nix",
          "type": "text",
          "primaryKey": false,
          "notNull": true,
          "autoincrement": false
        },
        "url": {
          "name": "url",
          "type": "text",
          "primaryKey": false,
          "notNull": true,
          "autoincrement": false
        },
        "created_at": {
          "name": "created_at",
          "type": "text",
          "primaryKey": false,
          "notNull": true,
          "autoincrement": false,
          "default": "(strftime('%Y-%m-%dT%H:%M:%SZ', 'now'))"
        }
      },
      "indexes": {},
      "foreignKeys": {},
      "compositePrimaryKeys": {
        "packages_pname_version_pk": {
          "columns": [
            "pname",
            "version"
          ],
          "name": "packages_pname_version_pk"
        }
      },
      "uniqueConstraints": {}
    }
  },
  "enums": {},
  "_meta": {
    "schemas": {},
    "tables": {},
    "columns": {}
  },
  "internal": {
    "indexes": {}
  }
}